<ExportPresets LastType="XlsxExport">
  <Preset DisplayName="" Type="DocxExport">
    <ExportSettings Type="DocxExport">
      <Filename>C:\Users\user\Desktop\ArticyUnannouncedProject.docx</Filename>
      <PageSize>Letter</PageSize>
      <GroupedBy>Folder</GroupedBy>
      <SortedBy>DisplayName</SortedBy>
      <HyperlinkOnReferences>1</HyperlinkOnReferences>
      <ExportMethod>Single</ExportMethod>
      <IncludeImages>1</IncludeImages>
      <SideBySideImages>0</SideBySideImages>
      <InsertTableOfContents>1</InsertTableOfContents>
      <IncludeTitlePage>1</IncludeTitlePage>
      <IncludeTechnicalNames>0</IncludeTechnicalNames>
      <ExportMarkup>1</ExportMarkup>
      <AutoOpenFile>1</AutoOpenFile>
      <ExportQueries>1</ExportQueries>
    </ExportSettings>
  </Preset>
  <Preset DisplayName="" Type="XlsxExport">
    <ExportSettings Type="XlsxExport">
      <Filename>C:\Users\user\Documents\ArticyUnannouncedProject.xlsx</Filename>
      <TablePerGroup>1</TablePerGroup>
      <GroupedBy>ObjectType</GroupedBy>
      <SortedBy>DisplayName</SortedBy>
      <WhichName>DisplayName</WhichName>
      <FeatureOrder>Alphabetical</FeatureOrder>
      <CollectStatistics>1</CollectStatistics>
      <ExportMarkup>0</ExportMarkup>
      <VariableOrder>Namespace</VariableOrder>
      <ExportQueries>False</ExportQueries>
      <PageSize>A4</PageSize>
      <AutoOpenFile>1</AutoOpenFile>
    </ExportSettings>
  </Preset>
</ExportPresets>
